.version 49 0
.class public super TestStringer
.super java/lang/Object
.field private static Z [Ljava/lang/Object;

.method public static main : ([Ljava/lang/String;)V
    .code stack 10 locals 10
        getstatic java/lang/System out Ljava/io/PrintStream;
        invokestatic TestStringer test (Ljava/io/PrintStream;)V
        return
    .end code
.end method

.method public static test : (Ljava/io/PrintStream;)V
    .code stack 100 locals 10
        invokestatic Method TestStringer o ()V
        aload_0
        getstatic TestStringer Z [Ljava/lang/Object;
        ldc 0
        aaload
        checkcast [B
        invokestatic java/util/Arrays toString ([B)Ljava/lang/String;
        invokevirtual java/io/PrintStream println (Ljava/lang/Object;)V
        aload_0
        getstatic TestStringer Z [Ljava/lang/Object;
        ldc 1
        aaload
        checkcast [I
        invokestatic java/util/Arrays toString ([I)Ljava/lang/String;
        invokevirtual java/io/PrintStream println (Ljava/lang/Object;)V
        aload_0
        getstatic TestStringer Z [Ljava/lang/Object;
        ldc 2
        aaload
        checkcast [I
        invokestatic java/util/Arrays toString ([I)Ljava/lang/String;
        invokevirtual java/io/PrintStream println (Ljava/lang/Object;)V
        aload_0
        getstatic TestStringer Z [Ljava/lang/Object;
        ldc 3
        aaload
        checkcast [I
        invokestatic java/util/Arrays toString ([I)Ljava/lang/String;
        invokevirtual java/io/PrintStream println (Ljava/lang/Object;)V
        aload_0
        getstatic TestStringer Z [Ljava/lang/Object;
        ldc 4
        aaload
        checkcast [I
        invokestatic java/util/Arrays toString ([I)Ljava/lang/String;
        invokevirtual java/io/PrintStream println (Ljava/lang/Object;)V
        aload_0
        getstatic TestStringer Z [Ljava/lang/Object;
        ldc 5
        aaload
        checkcast [I
        invokestatic java/util/Arrays toString ([I)Ljava/lang/String;
        invokevirtual java/io/PrintStream println (Ljava/lang/Object;)V
        aload_0
        getstatic TestStringer Z [Ljava/lang/Object;
        ldc 6
        aaload
        checkcast [I
        invokestatic java/util/Arrays toString ([I)Ljava/lang/String;
        invokevirtual java/io/PrintStream println (Ljava/lang/Object;)V
        return
    .end code
.end method

.method private static final w : (II)I
    .code stack 3 locals 6
L0:     iconst_0
L1:     istore 5
L3:     iload_0
L4:     istore_2
L5:     iload_1
L6:     istore_3
L7:     iload_3
L8:     iload_2
L9:     iadd
L10:    bipush 24
L12:    ishr
L13:    istore 4
L15:    goto L64
        .catch java/lang/Throwable from L18 to L36 using L18
L18:    iload 5
L20:    ifne L39
L23:    pop
L24:    iconst_3
L25:    istore 5
L27:    iload_0
L28:    iload_1
L29:    iushr
L30:    iload_0
L31:    iload_1
L32:    ineg
L33:    ishl
L34:    ior
L35:    istore_3
L36:    goto L62
L39:    astore_1
L40:    goto L71
        .catch java/lang/Throwable from L43 to L57 using L43
L43:    iload 5
L45:    ifne L60
L48:    pop
L49:    iinc 5 1
L52:    iload_2
L53:    iload 4
L55:    iadd
L56:    istore_3
L57:    goto L62
L60:    astore 4
L62:    iload_3
L63:    ireturn
L64:    iconst_0
L65:    istore 5
L67:    aconst_null
L68:    goto L18
L71:    iconst_0
L72:    istore 5
L74:    aconst_null
L75:    goto L43
L78:
    .end code
.end method

.method private static final D : ([BI)I
    .code stack 4 locals 5
L0:     iconst_0
L1:     istore 4
L3:     aload_0
L4:     bipush 10
L6:     baload
L7:     bipush 16
L9:     ishl
L10:    istore_2
L11:    goto L117
        .catch java/lang/Throwable from L14 to L85 using L14
L14:    iload 4
L16:    ifne L88
L19:    pop
L20:    iconst_3
L21:    istore 4
L23:    aload_0
L24:    iload_1
L25:    sipush 255
L28:    iand
L29:    baload
L30:    sipush 255
L33:    iand
L34:    aload_0
L35:    iload_1
L36:    bipush 8
L38:    ishr
L39:    sipush 255
L42:    iand
L43:    baload
L44:    sipush 255
L47:    iand
L48:    bipush 8
L50:    ishl
L51:    ior
L52:    aload_0
L53:    iload_1
L54:    bipush 16
L56:    ishr
L57:    sipush 255
L60:    iand
L61:    baload
L62:    sipush 255
L65:    iand
L66:    bipush 16
L68:    ishl
L69:    ior
L70:    aload_0
L71:    iload_1
L72:    bipush 24
L74:    ishr
L75:    sipush 255
L78:    iand
L79:    baload
L80:    bipush 24
L82:    ishl
L83:    ior
L84:    istore_2
L85:    goto L115
L88:    astore_3
L89:    goto L124
        .catch java/lang/Throwable from L92 to L111 using L92
L92:    iload 4
L94:    ifne L114
L97:    pop
L98:    iconst_2
L99:    istore 4
L101:   aload_0
L102:   iload_1
L103:   bipush 127
L105:   iand
L106:   baload
L107:   bipush 8
L109:   ishr
L110:   istore_2
L111:   goto L115
L114:   astore_3
L115:   iload_2
L116:   ireturn
L117:   iconst_0
L118:   istore 4
L120:   aconst_null
L121:   goto L14
L124:   iconst_0
L125:   istore 4
L127:   aconst_null
L128:   goto L92
L131:
    .end code
.end method

.method private static final R : (J)[B
    .code stack 7 locals 2
L0:     bipush 8
L2:     newarray byte
L4:     dup
L5:     iconst_0
L6:     lload_0
L7:     bipush 56
L9:     lshr
L10:    ldc2_w 255L
L13:    land
L14:    l2i
L15:    i2b
L16:    bastore
L17:    dup
L18:    iconst_1
L19:    lload_0
L20:    bipush 48
L22:    lshr
L23:    ldc2_w 255L
L26:    land
L27:    l2i
L28:    i2b
L29:    bastore
L30:    dup
L31:    iconst_2
L32:    lload_0
L33:    bipush 40
L35:    lshr
L36:    ldc2_w 255L
L39:    land
L40:    l2i
L41:    i2b
L42:    bastore
L43:    dup
L44:    iconst_3
L45:    lload_0
L46:    bipush 32
L48:    lshr
L49:    ldc2_w 255L
L52:    land
L53:    l2i
L54:    i2b
L55:    bastore
L56:    dup
L57:    iconst_4
L58:    lload_0
L59:    bipush 24
L61:    lshr
L62:    ldc2_w 255L
L65:    land
L66:    l2i
L67:    i2b
L68:    bastore
L69:    dup
L70:    iconst_5
L71:    lload_0
L72:    bipush 16
L74:    lshr
L75:    ldc2_w 255L
L78:    land
L79:    l2i
L80:    i2b
L81:    bastore
L82:    dup
L83:    bipush 6
L85:    lload_0
L86:    bipush 8
L88:    lshr
L89:    ldc2_w 255L
L92:    land
L93:    l2i
L94:    i2b
L95:    bastore
L96:    dup
L97:    bipush 7
L99:    lload_0
L100:   ldc2_w 255L
L103:   land
L104:   l2i
L105:   i2b
L106:   bastore
L107:   areturn
L108:
    .end code
.end method

.method private static final w : (J)J
    .code stack 6 locals 10
L0:     iconst_0
L1:     istore 9
L3:     lload_0
L4:     lstore_2
L5:     ldc2_w -988038576865741437L
L8:     lstore 4
L10:    lload 4
L12:    lload_2
L13:    ladd
L14:    bipush 24
L16:    lshr
L17:    lstore 6
L19:    goto L71
        .catch java/lang/Exception from L22 to L38 using L22
L22:    iload 9
L24:    ifne L41
L27:    pop
L28:    iinc 9 1
L31:    lload_0
L32:    lload_0
L33:    lload_2
L34:    lsub
L35:    ldiv
L36:    lstore 6
L38:    goto L68
L41:    astore 8
L43:    goto L78
        .catch java/lang/Exception from L46 to L63 using L46
L46:    iload 9
L48:    ifne L66
L51:    pop
L52:    iinc 9 3
L55:    lload 4
L57:    ldc2_w 102725110176638982L
L60:    ladd
L61:    lstore 4
L63:    goto L68
L66:    astore 8
L68:    lload 4
L70:    lreturn
L71:    iconst_0
L72:    istore 9
L74:    aconst_null
L75:    goto L22
L78:    iconst_0
L79:    istore 9
L81:    aconst_null
L82:    goto L46
L85:
    .end code
.end method

.method private static final i : ()J
    .code stack 2 locals 0
L0:     ldc2_w -8124380416302647420L
L3:     lreturn
L4:
    .end code
.end method

.method private static final o : ()V
    .code stack 6 locals 17
L0:     iconst_0
L1:     istore 15
L3:     iconst_0
L4:     istore 16
L6:     nop
L7:     sipush 256
L10:    newarray int
L12:    astore_0
L13:    sipush 256
L16:    newarray byte
L18:    astore_1
L19:    sipush 256
L22:    newarray int
L24:    astore_2
L25:    sipush 256
L28:    newarray int
L30:    astore_3
L31:    sipush 256
L34:    newarray int
L36:    astore 4
L38:    sipush 256
L41:    newarray int
L43:    astore 5
L45:    bipush 30
L47:    newarray int
L49:    astore 6
L51:    ldc2_w 9223372036854775807L
L54:    lstore 7
L56:    iconst_0
L57:    istore 9
L59:    iconst_1
L60:    istore 10
L62:    iload 9
L64:    sipush 256
L67:    if_icmpge L101
L70:    aload_0
L71:    iload 9
L73:    iload 10
L75:    iastore
L76:    iload 10
L78:    iload 10
L80:    iconst_1
L81:    ishl
L82:    iload 10
L84:    bipush 7
L86:    iushr
L87:    sipush 283
L90:    imul
L91:    ixor
L92:    ixor
L93:    istore 10
L95:    iinc 9 1
L98:    goto L62
L101:   aload_1
L102:   iconst_0
L103:   bipush 99
L105:   bastore
L106:   goto L902
        .catch java/lang/Exception from L109 to L349 using L109
L109:   iload 15
L111:   ifne L352
L114:   pop
L115:   iconst_1
L116:   istore 15
L118:   iconst_0
L119:   istore 10
L121:   iload 10
L123:   sipush 255
L126:   if_icmpge L184
L129:   aload_0
L130:   sipush 255
L133:   iload 10
L135:   isub
L136:   iaload
L137:   dup
L138:   bipush 8
L140:   ishl
L141:   ior
L142:   istore 9
L144:   aload_1
L145:   aload_0
L146:   iload 10
L148:   iaload
L149:   iload 9
L151:   iload 9
L153:   iconst_4
L154:   ishr
L155:   iload 9
L157:   iconst_5
L158:   ishr
L159:   ixor
L160:   iload 9
L162:   bipush 6
L164:   ishr
L165:   ixor
L166:   iload 9
L168:   bipush 7
L170:   ishr
L171:   ixor
L172:   ixor
L173:   bipush 99
L175:   ixor
L176:   i2b
L177:   bastore
L178:   iinc 10 1
L181:   goto L121
L184:   iconst_0
L185:   istore 9
L187:   iload 9
L189:   sipush 256
L192:   if_icmpge L307
L195:   aload_1
L196:   iload 9
L198:   baload
L199:   sipush 255
L202:   iand
L203:   istore 11
L205:   iload 11
L207:   iload 11
L209:   iconst_1
L210:   ishl
L211:   iload 11
L213:   bipush 7
L215:   iushr
L216:   sipush 283
L219:   imul
L220:   ixor
L221:   istore 10
L223:   iload 10
L225:   ixor
L226:   bipush 24
L228:   ishl
L229:   iload 11
L231:   bipush 16
L233:   ishl
L234:   ixor
L235:   iload 11
L237:   bipush 8
L239:   ishl
L240:   ixor
L241:   iload 10
L243:   ixor
L244:   iconst_m1
L245:   iand
L246:   istore 11
L248:   aload_2
L249:   iload 9
L251:   iload 11
L253:   iastore
L254:   aload_3
L255:   iload 9
L257:   iload 11
L259:   bipush 8
L261:   ishl
L262:   iload 11
L264:   bipush -8
L266:   iushr
L267:   ior
L268:   iastore
L269:   aload 4
L271:   iload 9
L273:   iload 11
L275:   bipush 16
L277:   ishl
L278:   iload 11
L280:   bipush -16
L282:   iushr
L283:   ior
L284:   iastore
L285:   aload 5
L287:   iload 9
L289:   iload 11
L291:   bipush 24
L293:   ishl
L294:   iload 11
L296:   bipush -24
L298:   iushr
L299:   ior
L300:   iastore
L301:   iinc 9 1
L304:   goto L187
L307:   iconst_0
L308:   istore 11
L310:   iconst_1
L311:   istore 10
L313:   iload 11
L315:   bipush 30
L317:   if_icmpge L349
L320:   aload 6
L322:   iload 11
L324:   iload 10
L326:   iastore
L327:   iload 10
L329:   iconst_1
L330:   ishl
L331:   iload 10
L333:   bipush 7
L335:   iushr
L336:   sipush 283
L339:   imul
L340:   ixor
L341:   istore 10
L343:   iinc 11 1
L346:   goto L313
L349:   goto L354
L352:   astore 11
L354:   bipush 16
L356:   newarray byte
L358:   astore 11
L360:   goto L909
        .catch java/lang/Exception from L363 to L409 using L363
        .catch java/lang/Throwable from L363 to L409 using L505
L363:   iload 15
L365:   ifne L440
L368:   pop
L369:   iconst_1
L370:   istore 15
L372:   invokestatic Method TestStringer i ()J
L375:   invokestatic Method TestStringer w (J)J
L378:   lload 7
L380:   invokestatic Method java/lang/System currentTimeMillis ()J
L383:   lsub
L384:   bipush 63
L386:   lshr
L387:   lconst_1
L388:   land
L389:   lxor
L390:   invokestatic Method TestStringer R (J)[B
L393:   iconst_0
L394:   aload 11
L396:   iconst_0
L397:   bipush 8
L399:   invokestatic Method java/lang/System arraycopy (Ljava/lang/Object;ILjava/lang/Object;II)V
L402:   aload 11
L404:   bipush 16
L406:   bipush -124
L408:   bastore
L409:   aload 11
L411:   bipush 12
L413:   bipush 98
L415:   bastore
L416:   aload 11
L418:   bipush 13
L420:   bipush 35
L422:   bastore
L423:   aload 11
L425:   bipush 14
L427:   bipush -9
L429:   bastore
L430:   aload 11
L432:   bipush 15
L434:   bipush -124
L436:   bastore
L437:   goto L542
L440:   astore 10
        .catch java/lang/Throwable from L442 to L474 using L505
L442:   aload 10
L444:   astore 10
L446:   aload 11
L448:   bipush 8
L450:   bipush -113
L452:   bastore
L453:   aload 11
L455:   bipush 9
L457:   bipush 64
L459:   bastore
L460:   aload 11
L462:   bipush 10
L464:   bipush 103
L466:   bastore
L467:   aload 11
L469:   bipush 11
L471:   bipush 14
L473:   bastore
L474:   aload 11
L476:   bipush 12
L478:   bipush 98
L480:   bastore
L481:   aload 11
L483:   bipush 13
L485:   bipush 35
L487:   bastore
L488:   aload 11
L490:   bipush 14
L492:   bipush -9
L494:   bastore
L495:   aload 11
L497:   bipush 15
L499:   bipush -124
L501:   bastore
L502:   goto L542
L505:   astore 10
        .catch java/lang/Throwable from L507 to L511 using L505
L507:   aload 10
L509:   astore 10
L511:   aload 11
L513:   bipush 12
L515:   bipush 98
L517:   bastore
L518:   aload 11
L520:   bipush 13
L522:   bipush 35
L524:   bastore
L525:   aload 11
L527:   bipush 14
L529:   bipush -9
L531:   bastore
L532:   aload 11
L534:   bipush 15
L536:   bipush -124
L538:   bastore
L539:   aload 10
L541:   athrow
L542:   iconst_4
L543:   istore 9
L545:   iload 9
L547:   bipush 6
L549:   iadd
L550:   istore_0
L551:   iload_0
L552:   iconst_1
L553:   iadd
L554:   iconst_4
L555:   imul
L556:   newarray int
L558:   astore 12
L560:   goto L923
L563:   iload 16
L565:   ifne L818
L568:   pop
L569:   iinc 16 1
L572:   iconst_0
L573:   istore 13
L575:   iconst_0
L576:   istore 10
L578:   goto L916
        .catch java/lang/Exception from L581 to L670 using L581
        .catch java/lang/Exception from L563 to L815 using L563
L581:   iload 15
L583:   ifne L673
L586:   pop
L587:   iconst_2
L588:   istore 15
L590:   iload 10
L592:   bipush 16
L594:   if_icmpge L670
L597:   aload 12
L599:   iload 13
L601:   iconst_2
L602:   ishr
L603:   iconst_4
L604:   imul
L605:   iload 13
L607:   iadd
L608:   iconst_3
L609:   iand
L610:   aload 11
L612:   iload 10
L614:   baload
L615:   sipush 255
L618:   iand
L619:   aload 11
L621:   iload 10
L623:   iconst_1
L624:   iadd
L625:   baload
L626:   sipush 255
L629:   iand
L630:   bipush 8
L632:   ishl
L633:   ior
L634:   aload 11
L636:   iload 10
L638:   iconst_2
L639:   iadd
L640:   baload
L641:   sipush 255
L644:   iand
L645:   bipush 16
L647:   ishl
L648:   ior
L649:   aload 11
L651:   iload 10
L653:   iconst_3
L654:   iadd
L655:   baload
L656:   bipush 24
L658:   ishl
L659:   ior
L660:   iastore
L661:   iinc 10 4
L664:   iinc 13 1
L667:   goto L916
L670:   goto L675
L673:   astore 10
L675:   iload_0
L676:   iconst_1
L677:   iadd
L678:   iconst_2
L679:   ishl
L680:   istore 13
L682:   iload 9
L684:   istore 14
L686:   iload 14
L688:   iload 13
L690:   if_icmpge L815
L693:   aload 12
L695:   iload 14
L697:   iconst_1
L698:   isub
L699:   iconst_2
L700:   ishr
L701:   iconst_4
L702:   imul
L703:   iload 14
L705:   iconst_1
L706:   isub
L707:   iconst_3
L708:   iand
L709:   iadd
L710:   iaload
L711:   istore 10
L713:   iload 14
L715:   iload 9
L717:   irem
L718:   ifne L748
L721:   aload_1
L722:   iload 10
L724:   bipush 8
L726:   invokestatic Method TestStringer w (II)I
L729:   invokestatic Method TestStringer D ([BI)I
L732:   aload 6
L734:   iload 14
L736:   iload 9
L738:   idiv
L739:   iconst_1
L740:   isub
L741:   iaload
L742:   ixor
L743:   istore 10
L745:   goto L772
L748:   iload 9
L750:   bipush 6
L752:   if_icmple L772
L755:   iload 14
L757:   iload 9
L759:   irem
L760:   iconst_4
L761:   if_icmpne L772
L764:   aload_1
L765:   iload 10
L767:   invokestatic Method TestStringer D ([BI)I
L770:   istore 10
L772:   aload 12
L774:   iload 14
L776:   iconst_2
L777:   ishr
L778:   iconst_4
L779:   imul
L780:   iload 14
L782:   iconst_3
L783:   iand
L784:   iadd
L785:   aload 12
L787:   iload 14
L789:   iload 9
L791:   isub
L792:   iconst_2
L793:   ishr
L794:   iconst_4
L795:   imul
L796:   iload 14
L798:   iload 9
L800:   isub
L801:   iconst_3
L802:   iand
L803:   iadd
L804:   iaload
L805:   iload 10
L807:   ixor
L808:   iastore
L809:   iinc 14 1
L812:   goto L686
L815:   goto L820
L818:   astore 14
L820:   iconst_4
L821:   newarray int
L823:   astore 14
L825:   aload 14
L827:   iconst_0
L828:   ldc 1250131200
L830:   iastore
L831:   aload 14
L833:   iconst_1
L834:   ldc 1084471788
L836:   iastore
L837:   aload 14
L839:   iconst_2
L840:   ldc 590773236
L842:   iastore
L843:   aload 14
L845:   iconst_3
L846:   ldc 1318903609
L848:   iastore
L849:   bipush 7
L851:   anewarray java/lang/Object
L854:   astore 13
L856:   aload 13
L858:   iconst_0
L859:   aload_1
L860:   aastore
L861:   aload 13
L863:   iconst_1
L864:   aload_2
L865:   aastore
L866:   aload 13
L868:   iconst_2
L869:   aload_3
L870:   aastore
L871:   aload 13
L873:   iconst_3
L874:   aload 4
L876:   aastore
L877:   aload 13
L879:   iconst_4
L880:   aload 5
L882:   aastore
L883:   aload 13
L885:   iconst_5
L886:   aload 12
L888:   aastore
L889:   aload 13
L891:   bipush 6
L893:   aload 14
L895:   aastore
L896:   aload 13
L898:   putstatic Field TestStringer Z [Ljava/lang/Object;
L901:   return
L902:   iconst_0
L903:   istore 15
L905:   aconst_null
L906:   goto L109
L909:   iconst_0
L910:   istore 15
L912:   aconst_null
L913:   goto L363
L916:   iconst_0
L917:   istore 15
L919:   aconst_null
L920:   goto L581
L923:   iconst_0
L924:   istore 16
L926:   aconst_null
L927:   goto L563
L930:
    .end code
.end method

.method static final b : (Ljava/lang/Object;)Ljava/lang/String;
    .code stack 5 locals 23
L0:     iconst_0
L1:     istore 21
L3:     iconst_0
L4:     istore 22
L6:     getstatic Field TestStringer Z [Ljava/lang/Object;
L9:     ifnonnull L15
L12:    invokestatic Method TestStringer o ()V
L15:    getstatic Field TestStringer Z [Ljava/lang/Object;
L18:    bipush 6
L20:    aaload
L21:    checkcast [I
L24:    checkcast [I
L27:    astore_1
L28:    aload_1
L29:    iconst_0
L30:    iaload
L31:    istore_2
L32:    aload_1
L33:    iconst_1
L34:    iaload
L35:    istore_3
L36:    aload_1
L37:    iconst_2
L38:    iaload
L39:    istore 4
L41:    aload_1
L42:    iconst_3
L43:    iaload
L44:    istore_1
L45:    getstatic Field TestStringer Z [Ljava/lang/Object;
L48:    iconst_5
L49:    aaload
L50:    checkcast [I
L53:    checkcast [I
L56:    astore 5
L58:    getstatic Field TestStringer Z [Ljava/lang/Object;
L61:    iconst_1
L62:    aaload
L63:    checkcast [I
L66:    checkcast [I
L69:    astore 6
L71:    getstatic Field TestStringer Z [Ljava/lang/Object;
L74:    iconst_2
L75:    aaload
L76:    checkcast [I
L79:    checkcast [I
L82:    astore 7
L84:    getstatic Field TestStringer Z [Ljava/lang/Object;
L87:    iconst_3
L88:    aaload
L89:    checkcast [I
L92:    checkcast [I
L95:    astore 8
L97:    getstatic Field TestStringer Z [Ljava/lang/Object;
L100:   iconst_4
L101:   aaload
L102:   checkcast [I
L105:   checkcast [I
L108:   astore 9
L110:   getstatic Field TestStringer Z [Ljava/lang/Object;
L113:   iconst_0
L114:   aaload
L115:   checkcast [B
L118:   checkcast [B
L121:   astore 10
L123:   aload_0
L124:   checkcast java/lang/String
L127:   invokevirtual Method java/lang/String toCharArray ()[C
L130:   astore_0
L131:   goto L1399
L134:   iload 22
L136:   ifne L1381
L139:   pop
L140:   iinc 22 2
L143:   aload_0
L144:   arraylength
L145:   istore 11
L147:   iconst_0
L148:   istore 12
L150:   iload 12
L152:   iload 11
L154:   if_icmpge L1378
L157:   iload 12
L159:   bipush 8
L161:   irem
L162:   ifne L1392
L165:   iconst_0
L166:   istore 13
L168:   iconst_0
L169:   istore 13
L171:   iconst_0
L172:   istore 13
L174:   iconst_0
L175:   istore 13
L177:   iload_2
L178:   aload 5
L180:   iconst_0
L181:   iaload
L182:   ixor
L183:   istore 14
L185:   iload_3
L186:   aload 5
L188:   iconst_1
L189:   iaload
L190:   ixor
L191:   istore 15
L193:   iload 4
L195:   aload 5
L197:   iconst_2
L198:   iaload
L199:   ixor
L200:   istore 16
L202:   iload_1
L203:   aload 5
L205:   iconst_3
L206:   iaload
L207:   ixor
L208:   istore 17
L210:   iconst_4
L211:   istore 13
L213:   iload 13
L215:   bipush 36
L217:   if_icmpge L663
L220:   aload 6
L222:   iload 14
L224:   sipush 255
L227:   iand
L228:   iaload
L229:   aload 7
L231:   iload 15
L233:   bipush 8
L235:   ishr
L236:   sipush 255
L239:   iand
L240:   iaload
L241:   ixor
L242:   aload 8
L244:   iload 16
L246:   bipush 16
L248:   ishr
L249:   sipush 255
L252:   iand
L253:   iaload
L254:   ixor
L255:   aload 9
L257:   iload 17
L259:   bipush 24
L261:   iushr
L262:   iaload
L263:   ixor
L264:   aload 5
L266:   iload 13
L268:   iaload
L269:   ixor
L270:   istore 18
L272:   aload 6
L274:   iload 15
L276:   sipush 255
L279:   iand
L280:   iaload
L281:   aload 7
L283:   iload 16
L285:   bipush 8
L287:   ishr
L288:   sipush 255
L291:   iand
L292:   iaload
L293:   ixor
L294:   aload 8
L296:   iload 17
L298:   bipush 16
L300:   ishr
L301:   sipush 255
L304:   iand
L305:   iaload
L306:   ixor
L307:   aload 9
L309:   iload 14
L311:   bipush 24
L313:   iushr
L314:   iaload
L315:   ixor
L316:   aload 5
L318:   iload 13
L320:   iconst_1
L321:   iadd
L322:   iaload
L323:   ixor
L324:   istore 19
L326:   aload 6
L328:   iload 16
L330:   sipush 255
L333:   iand
L334:   iaload
L335:   aload 7
L337:   iload 17
L339:   bipush 8
L341:   ishr
L342:   sipush 255
L345:   iand
L346:   iaload
L347:   ixor
L348:   aload 8
L350:   iload 14
L352:   bipush 16
L354:   ishr
L355:   sipush 255
L358:   iand
L359:   iaload
L360:   ixor
L361:   aload 9
L363:   iload 15
L365:   bipush 24
L367:   iushr
L368:   iaload
L369:   ixor
L370:   aload 5
L372:   iload 13
L374:   iconst_2
L375:   iadd
L376:   iaload
L377:   ixor
L378:   istore 20
L380:   aload 6
L382:   iload 17
L384:   sipush 255
L387:   iand
L388:   iaload
L389:   aload 7
L391:   iload 14
L393:   bipush 8
L395:   ishr
L396:   sipush 255
L399:   iand
L400:   iaload
L401:   ixor
L402:   aload 8
L404:   iload 15
L406:   bipush 16
L408:   ishr
L409:   sipush 255
L412:   iand
L413:   iaload
L414:   ixor
L415:   aload 9
L417:   iload 16
L419:   bipush 24
L421:   iushr
L422:   iaload
L423:   ixor
L424:   aload 5
L426:   iload 13
L428:   iconst_3
L429:   iadd
L430:   iaload
L431:   ixor
L432:   istore 17
L434:   iload 13
L436:   iconst_4
L437:   iadd
L438:   istore 13
L440:   aload 6
L442:   iload 18
L444:   sipush 255
L447:   iand
L448:   iaload
L449:   aload 7
L451:   iload 19
L453:   bipush 8
L455:   ishr
L456:   sipush 255
L459:   iand
L460:   iaload
L461:   ixor
L462:   aload 8
L464:   iload 20
L466:   bipush 16
L468:   ishr
L469:   sipush 255
L472:   iand
L473:   iaload
L474:   ixor
L475:   aload 9
L477:   iload 17
L479:   bipush 24
L481:   iushr
L482:   iaload
L483:   ixor
L484:   aload 5
L486:   iload 13
L488:   iaload
L489:   ixor
L490:   istore 14
L492:   aload 6
L494:   iload 19
L496:   sipush 255
L499:   iand
L500:   iaload
L501:   aload 7
L503:   iload 20
L505:   bipush 8
L507:   ishr
L508:   sipush 255
L511:   iand
L512:   iaload
L513:   ixor
L514:   aload 8
L516:   iload 17
L518:   bipush 16
L520:   ishr
L521:   sipush 255
L524:   iand
L525:   iaload
L526:   ixor
L527:   aload 9
L529:   iload 18
L531:   bipush 24
L533:   iushr
L534:   iaload
L535:   ixor
L536:   aload 5
L538:   iload 13
L540:   iconst_1
L541:   iadd
L542:   iaload
L543:   ixor
L544:   istore 15
L546:   aload 6
L548:   iload 20
L550:   sipush 255
L553:   iand
L554:   iaload
L555:   aload 7
L557:   iload 17
L559:   bipush 8
L561:   ishr
L562:   sipush 255
L565:   iand
L566:   iaload
L567:   ixor
L568:   aload 8
L570:   iload 18
L572:   bipush 16
L574:   ishr
L575:   sipush 255
L578:   iand
L579:   iaload
L580:   ixor
L581:   aload 9
L583:   iload 19
L585:   bipush 24
L587:   iushr
L588:   iaload
L589:   ixor
L590:   aload 5
L592:   iload 13
L594:   iconst_2
L595:   iadd
L596:   iaload
L597:   ixor
L598:   istore 16
L600:   aload 6
L602:   iload 17
L604:   sipush 255
L607:   iand
L608:   iaload
L609:   aload 7
L611:   iload 18
L613:   bipush 8
L615:   ishr
L616:   sipush 255
L619:   iand
L620:   iaload
L621:   ixor
L622:   aload 8
L624:   iload 19
L626:   bipush 16
L628:   ishr
L629:   sipush 255
L632:   iand
L633:   iaload
L634:   ixor
L635:   aload 9
L637:   iload 20
L639:   bipush 24
L641:   iushr
L642:   iaload
L643:   ixor
L644:   aload 5
L646:   iload 13
L648:   iconst_3
L649:   iadd
L650:   iaload
L651:   ixor
L652:   istore 17
L654:   iload 13
L656:   iconst_4
L657:   iadd
L658:   istore 13
L660:   goto L213
L663:   aload 6
L665:   iload 14
L667:   sipush 255
L670:   iand
L671:   iaload
L672:   aload 7
L674:   iload 15
L676:   bipush 8
L678:   ishr
L679:   sipush 255
L682:   iand
L683:   iaload
L684:   ixor
L685:   aload 8
L687:   iload 16
L689:   bipush 16
L691:   ishr
L692:   sipush 255
L695:   iand
L696:   iaload
L697:   ixor
L698:   aload 9
L700:   iload 17
L702:   bipush 24
L704:   iushr
L705:   iaload
L706:   ixor
L707:   aload 5
L709:   iload 13
L711:   iaload
L712:   ixor
L713:   istore 20
L715:   aload 6
L717:   iload 15
L719:   sipush 255
L722:   iand
L723:   iaload
L724:   aload 7
L726:   iload 16
L728:   bipush 8
L730:   ishr
L731:   sipush 255
L734:   iand
L735:   iaload
L736:   ixor
L737:   aload 8
L739:   iload 17
L741:   bipush 16
L743:   ishr
L744:   sipush 255
L747:   iand
L748:   iaload
L749:   ixor
L750:   aload 9
L752:   iload 14
L754:   bipush 24
L756:   iushr
L757:   iaload
L758:   ixor
L759:   aload 5
L761:   iload 13
L763:   iconst_1
L764:   iadd
L765:   iaload
L766:   ixor
L767:   istore 19
L769:   aload 6
L771:   iload 16
L773:   sipush 255
L776:   iand
L777:   iaload
L778:   aload 7
L780:   iload 17
L782:   bipush 8
L784:   ishr
L785:   sipush 255
L788:   iand
L789:   iaload
L790:   ixor
L791:   aload 8
L793:   iload 14
L795:   bipush 16
L797:   ishr
L798:   sipush 255
L801:   iand
L802:   iaload
L803:   ixor
L804:   aload 9
L806:   iload 15
L808:   bipush 24
L810:   iushr
L811:   iaload
L812:   ixor
L813:   aload 5
L815:   iload 13
L817:   iconst_2
L818:   iadd
L819:   iaload
L820:   ixor
L821:   istore 18
L823:   aload 6
L825:   iload 17
L827:   sipush 255
L830:   iand
L831:   iaload
L832:   aload 7
L834:   iload 14
L836:   bipush 8
L838:   ishr
L839:   sipush 255
L842:   iand
L843:   iaload
L844:   ixor
L845:   aload 8
L847:   iload 15
L849:   bipush 16
L851:   ishr
L852:   sipush 255
L855:   iand
L856:   iaload
L857:   ixor
L858:   aload 9
L860:   iload 16
L862:   bipush 24
L864:   iushr
L865:   iaload
L866:   ixor
L867:   aload 5
L869:   iload 13
L871:   iconst_3
L872:   iadd
L873:   iaload
L874:   ixor
L875:   istore 17
L877:   iload 13
L879:   iconst_4
L880:   iadd
L881:   istore 16
L883:   aload 10
L885:   iload 20
L887:   sipush 255
L890:   iand
L891:   baload
L892:   sipush 255
L895:   iand
L896:   aload 10
L898:   iload 19
L900:   bipush 8
L902:   ishr
L903:   sipush 255
L906:   iand
L907:   baload
L908:   sipush 255
L911:   iand
L912:   bipush 8
L914:   ishl
L915:   ixor
L916:   aload 10
L918:   iload 18
L920:   bipush 16
L922:   ishr
L923:   sipush 255
L926:   iand
L927:   baload
L928:   sipush 255
L931:   iand
L932:   bipush 16
L934:   ishl
L935:   ixor
L936:   aload 10
L938:   iload 17
L940:   bipush 24
L942:   iushr
L943:   baload
L944:   bipush 24
L946:   ishl
L947:   ixor
L948:   aload 5
L950:   iload 16
L952:   iconst_0
L953:   iadd
L954:   iaload
L955:   ixor
L956:   istore_2
L957:   aload 10
L959:   iload 19
L961:   sipush 255
L964:   iand
L965:   baload
L966:   sipush 255
L969:   iand
L970:   aload 10
L972:   iload 18
L974:   bipush 8
L976:   ishr
L977:   sipush 255
L980:   iand
L981:   baload
L982:   sipush 255
L985:   iand
L986:   bipush 8
L988:   ishl
L989:   ixor
L990:   aload 10
L992:   iload 17
L994:   bipush 16
L996:   ishr
L997:   sipush 255
L1000:  iand
L1001:  baload
L1002:  sipush 255
L1005:  iand
L1006:  bipush 16
L1008:  ishl
L1009:  ixor
L1010:  aload 10
L1012:  iload 20
L1014:  bipush 24
L1016:  iushr
L1017:  baload
L1018:  bipush 24
L1020:  ishl
L1021:  ixor
L1022:  aload 5
L1024:  iload 16
L1026:  iconst_1
L1027:  iadd
L1028:  iaload
L1029:  ixor
L1030:  istore_3
L1031:  aload 10
L1033:  iload 18
L1035:  sipush 255
L1038:  iand
L1039:  baload
L1040:  sipush 255
L1043:  iand
L1044:  aload 10
L1046:  iload 17
L1048:  bipush 8
L1050:  ishr
L1051:  sipush 255
L1054:  iand
L1055:  baload
L1056:  sipush 255
L1059:  iand
L1060:  bipush 8
L1062:  ishl
L1063:  ixor
L1064:  aload 10
L1066:  iload 20
L1068:  bipush 16
L1070:  ishr
L1071:  sipush 255
L1074:  iand
L1075:  baload
L1076:  sipush 255
L1079:  iand
L1080:  bipush 16
L1082:  ishl
L1083:  ixor
L1084:  aload 10
L1086:  iload 19
L1088:  bipush 24
L1090:  iushr
L1091:  baload
L1092:  bipush 24
L1094:  ishl
L1095:  ixor
L1096:  aload 5
L1098:  iload 16
L1100:  iconst_2
L1101:  iadd
L1102:  iaload
L1103:  ixor
L1104:  istore 4
L1106:  aload 10
L1108:  iload 17
L1110:  sipush 255
L1113:  iand
L1114:  baload
L1115:  sipush 255
L1118:  iand
L1119:  aload 10
L1121:  iload 20
L1123:  bipush 8
L1125:  ishr
L1126:  sipush 255
L1129:  iand
L1130:  baload
L1131:  sipush 255
L1134:  iand
L1135:  bipush 8
L1137:  ishl
L1138:  ixor
L1139:  aload 10
L1141:  iload 19
L1143:  bipush 16
L1145:  ishr
L1146:  sipush 255
L1149:  iand
L1150:  baload
L1151:  sipush 255
L1154:  iand
L1155:  bipush 16
L1157:  ishl
L1158:  ixor
L1159:  aload 10
L1161:  iload 18
L1163:  bipush 24
L1165:  iushr
L1166:  baload
L1167:  bipush 24
L1169:  ishl
L1170:  ixor
L1171:  aload 5
L1173:  iload 16
L1175:  iconst_3
L1176:  iadd
L1177:  iaload
L1178:  ixor
L1179:  istore_1
L1180:  goto L1392
        .catch java/lang/Exception from L1183 to L1367 using L1183
        .catch java/lang/Exception from L134 to L1378 using L134
L1183:  iload 21
L1185:  ifne L1370
L1188:  pop
L1189:  iconst_2
L1190:  istore 21
L1192:  iload 12
L1194:  bipush 8
L1196:  irem
L1197:  tableswitch 0
            L1244
            L1261
            L1275
            L1292
            L1306
            L1324
            L1339
            L1356
            default : L1367

L1244:  aload_0
L1245:  iload 12
L1247:  iload_2
L1248:  bipush 16
L1250:  ishr
L1251:  aload_0
L1252:  iload 12
L1254:  caload
L1255:  ixor
L1256:  i2c
L1257:  castore
L1258:  goto L1367
L1261:  aload_0
L1262:  iload 12
L1264:  iload_2
L1265:  aload_0
L1266:  iload 12
L1268:  caload
L1269:  ixor
L1270:  i2c
L1271:  castore
L1272:  goto L1367
L1275:  aload_0
L1276:  iload 12
L1278:  iload_3
L1279:  bipush 16
L1281:  ishr
L1282:  aload_0
L1283:  iload 12
L1285:  caload
L1286:  ixor
L1287:  i2c
L1288:  castore
L1289:  goto L1367
L1292:  aload_0
L1293:  iload 12
L1295:  iload_3
L1296:  aload_0
L1297:  iload 12
L1299:  caload
L1300:  ixor
L1301:  i2c
L1302:  castore
L1303:  goto L1367
L1306:  aload_0
L1307:  iload 12
L1309:  iload 4
L1311:  bipush 16
L1313:  ishr
L1314:  aload_0
L1315:  iload 12
L1317:  caload
L1318:  ixor
L1319:  i2c
L1320:  castore
L1321:  goto L1367
L1324:  aload_0
L1325:  iload 12
L1327:  iload 4
L1329:  aload_0
L1330:  iload 12
L1332:  caload
L1333:  ixor
L1334:  i2c
L1335:  castore
L1336:  goto L1367
L1339:  aload_0
L1340:  iload 12
L1342:  iload_1
L1343:  bipush 16
L1345:  ishr
L1346:  aload_0
L1347:  iload 12
L1349:  caload
L1350:  ixor
L1351:  i2c
L1352:  castore
L1353:  goto L1367
L1356:  aload_0
L1357:  iload 12
L1359:  iload_1
L1360:  aload_0
L1361:  iload 12
L1363:  caload
L1364:  ixor
L1365:  i2c
L1366:  castore
L1367:  goto L1372
L1370:  astore 13
L1372:  iinc 12 1
L1375:  goto L150
L1378:  goto L1383
L1381:  astore 20
L1383:  new java/lang/String
L1386:  dup
L1387:  aload_0
L1388:  invokespecial Method java/lang/String <init> ([C)V
L1391:  areturn
L1392:  iconst_0
L1393:  istore 21
L1395:  aconst_null
L1396:  goto L1183
L1399:  iconst_0
L1400:  istore 22
L1402:  aconst_null
L1403:  goto L134
L1406:
    .end code
.end method
.end class
